.gitignore
LICENSE
README.md
requirements.txt
setup.py
Jskit/.gitignore
Jskit/__init__.py
Jskit/autogui.py
Jskit/autogui_get_position.py
Jskit/autoom.py
Jskit/crawler.py
Jskit/pip_upgrade_all.py
Jskit/rename.py
Jskit.egg-info/PKG-INFO
Jskit.egg-info/PKG-INFO_JAKK-XM_1月-23-081224-2019_Conflict
Jskit.egg-info/SOURCES.txt
Jskit.egg-info/dependency_links.txt
Jskit.egg-info/requires.txt
Jskit.egg-info/top_level.txt