Metadata-Version: 1.0
Name: Jskit
Version: 0.2.2
Summary: A personal tool kit
Home-page: https://github.com/Jakkwj/Jskit
Author: JunWang
Author-email: shutupwj@163.com
License: Apache License Version 2.0
Keywords: pip,tool kit
Platform: any
